dxflow/api_tools.py
dxflow/authentication.py
dxflow/compute.py
dxflow/compute_type_manager.py
dxflow/config.py
dxflow/container.py
dxflow/flow.py
dxflow/project.py
dxflow/session.py
dxflow/storage.py
dxflow/utils/__init__.py
dxflow/utils/file_utils.py
dxflow/utils/utils.py
dxflow-0.1.7.dist-info/METADATA
dxflow-0.1.7.dist-info/WHEEL
dxflow-0.1.7.dist-info/top_level.txt
dxflow-0.1.7.dist-info/RECORD
