Metadata-Version: 2.4
Name: dxflow
Version: 0.1.7
Summary: A Python SDK for dxflow
Home-page: https://dxflow.ai
Author: DiPhyx Team
Author-email: DiPhyx Team <info@diphyx.com>
License: MIT
Project-URL: Homepage, https://diphyx.com
Project-URL: Repository, https://github.com/diphyx/dxflow
Project-URL: Issues, https://github.com/diphyx/dxflow/issues
Keywords: scientific computing,bioinformatic,cloud computing
Classifier: Programming Language :: Python :: 3
Classifier: Operating System :: OS Independent
Classifier: Development Status :: 4 - Beta
Classifier: Intended Audience :: Developers
Classifier: Topic :: Scientific/Engineering :: Bio-Informatics
Requires-Python: >=3.6, <4
Requires-Dist: requests>=2.26.0
Requires-Dist: pyyaml>=5.4.1
Requires-Dist: colorama>=0.4.4
Dynamic: author
Dynamic: home-page
Dynamic: requires-python
